<?xml version="1.0" encoding="UTF-8"?>
<!DOCTYPE mapper PUBLIC "-//mybatis.org//DTD Mapper 3.0//EN" "http://mybatis.org/dtd/mybatis-3-mapper.dtd">
<mapper namespace="management.community.xiaonong.mapper.AdminMapper">
  <resultMap id="BaseResultMap" type="management.community.xiaonong.model.Admin">
    <!--
      WARNING - @mbg.generated
      This element is automatically generated by MyBatis Generator, do not modify.
      This element was generated on Wed Mar 25 17:01:12 CST 2020.
    -->
    <result column="id" jdbcType="INTEGER" property="id" />
    <result column="username" jdbcType="VARCHAR" property="username" />
    <result column="password" jdbcType="VARCHAR" property="password" />
  </resultMap>
  <insert id="insert" parameterType="management.community.xiaonong.model.Admin">
    <!--
      WARNING - @mbg.generated
      This element is automatically generated by MyBatis Generator, do not modify.
      This element was generated on Wed Mar 25 17:01:12 CST 2020.
    -->
    insert into admin (id, username, password
      )
    values (#{id,jdbcType=INTEGER}, #{username,jdbcType=VARCHAR}, #{password,jdbcType=VARCHAR}
      )
  </insert>
  <insert id="insertSelective" parameterType="management.community.xiaonong.model.Admin">
    <!--
      WARNING - @mbg.generated
      This element is automatically generated by MyBatis Generator, do not modify.
      This element was generated on Wed Mar 25 17:01:12 CST 2020.
    -->
    insert into admin
    <trim prefix="(" suffix=")" suffixOverrides=",">
      <if test="id != null">
        id,
      </if>
      <if test="username != null">
        username,
      </if>
      <if test="password != null">
        password,
      </if>
    </trim>
    <trim prefix="values (" suffix=")" suffixOverrides=",">
      <if test="id != null">
        #{id,jdbcType=INTEGER},
      </if>
      <if test="username != null">
        #{username,jdbcType=VARCHAR},
      </if>
      <if test="password != null">
        #{password,jdbcType=VARCHAR},
      </if>
    </trim>
  </insert>

  <!--管理员登陆-->
  <select id="selectByUandP" resultType="java.lang.Integer">
    select count(*) from admin
    where
    username=#{username,jdbcType=VARCHAR}
    and
    password=#{password,jdbcType=VARCHAR};
  </select>
</mapper>